gpatches/__init__.py
gpatches-0.1.1.dist-info/METADATA
gpatches-0.1.1.dist-info/WHEEL
gpatches-0.1.1.dist-info/top_level.txt
gpatches-0.1.1.dist-info/RECORD
